{
  "totalPostCounts": {
    "monthlyPageViews": 939,
    "totalVisitors": 785,
    "totalMonthlyVisitors": 208
  },
  "rankingPosts": [
    {
      "url": "https://devblogeasyoon.xyz/blog/frontend-performance-pattern-korean",
      "title": "[번역] 프론트엔드 성능 패턴"
    },
    {
      "url": "https://devblogeasyoon.xyz/blog/the-future-of-front-end-development-trends-to-watch-in-2025",
      "title": "[번역] 2025년 프론트엔드 개발의 미래: 주목해야 할 트렌드"
    },
    {
      "url": "https://devblogeasyoon.xyz/blog/advanced-react-19",
      "title": "[번역] 예제 코드와 함께 보는 새로운 리엑트 v19 심화편"
    },
    {
      "url": "https://devblogeasyoon.xyz/blog/next-js-sharp-image-optimization",
      "title": "Sharp(Next의 이미지 최적화 라이브러리)의 효과는 대단했다 (+ Next/Image)"
    },
    {
      "url": "https://devblogeasyoon.xyz/blog/mui-vs-tailwind",
      "title": "Tailwind VS MUI (CSS Framework)"
    },
    {
      "url": "https://devblogeasyoon.xyz/blog/naver-interview-review",
      "title": "[회고] 프론트엔드 기술 면접 후기 - 네이버 파이낸셜"
    },
    {
      "url": "https://devblogeasyoon.xyz/blog/throttle-in-animation",
      "title": "JavaScript에서 Throttle을 사용한 애니메이션 구현"
    },
    {
      "url": "https://devblogeasyoon.xyz/blog/block-chain-words-dictionary",
      "title": "Blockchain Vocabulary for Review"
    },
    {
      "url": "https://devblogeasyoon.xyz/blog/summary-of-dapp-js-development-web3-ethers-js",
      "title": "Comparing ethers.js and web3.js as Web3 Regains Popularity"
    },
    {
      "url": "https://devblogeasyoon.xyz/blog/csr-routing-error-in-ghpages",
      "title": "[Solved] CSR(react)을 이용해서 gh-pages 배포를 할 때 생기는 라우팅 문제(새로고침, 404 등)"
    },
    {
      "url": "https://devblogeasyoon.xyz/blog/summary-of-dapp-js-development-web3-ethers-js",
      "title": "[Part 1]Comparing ethers.js and web3.js as Web3 Regains Popularity"
    },
    {
      "url": "https://devblogeasyoon.xyz/blog/beyond-code-finding-joy-in-global-tech-communites",
      "title": "해외 기술 커뮤니티에 포스팅하면서 얻는 소소한 즐거움과 깨달음"
    }
  ],
  "updateDate": "3/3 "
}
